enumset/__init__.py
enumset/enumset.py
enumset/flagset.py
enumset/iface.py
enumset/version.py
enumset-0.2.0.dist-info/LICENSE
enumset-0.2.0.dist-info/METADATA
enumset-0.2.0.dist-info/WHEEL
enumset-0.2.0.dist-info/top_level.txt
enumset-0.2.0.dist-info/zip-safe
enumset-0.2.0.dist-info/RECORD
