Metadata-Version: 2.1
Name: enumset
Version: 0.2.0
Summary: set of enum.Enum
Home-page: https://github.com/wtnb75/enumset
Author: Watanebe Takashi
Author-email: wtnb75@gmail.com
License: MIT
Classifier: Development Status :: 3 - Alpha
Classifier: Intended Audience :: Developers
Classifier: License :: OSI Approved :: MIT License
Classifier: Topic :: Software Development :: Libraries :: Python Modules
Classifier: Programming Language :: Python :: 3
License-File: LICENSE
Provides-Extra: dev
Requires-Dist: pytest ; extra == 'dev'
